lsdembed/__init__.py
lsdembed/_lsd_core.cpython-312-x86_64-linux-gnu.so
lsdembed/core.py
lsdembed/text_processor.py
lsdembed/utils.py
lsdembed-0.3.0.dist-info/METADATA
lsdembed-0.3.0.dist-info/WHEEL
lsdembed-0.3.0.dist-info/top_level.txt
lsdembed-0.3.0.dist-info/RECORD
lsdembed-0.3.0.dist-info/licenses/LICENSE
