Metadata-Version: 2.4
Name: lsdembed
Version: 0.3.0
Summary: Physics-inspired text embedding library
Author-email: Ritwik Singh <officialritwik098@gmail.com>
License-Expression: MIT
Project-URL: Homepage, https://github.com/datasciritwik/lsdembed
Project-URL: Repository, https://github.com/datasciritwik/lsdembed
Project-URL: Issues, https://github.com/datasciritwik/lsdembed/issues
Keywords: text-embeddings,nlp,physics,text-processing,machine-learning
Classifier: Development Status :: 3 - Alpha
Classifier: Intended Audience :: Developers
Classifier: Intended Audience :: Science/Research
Classifier: Programming Language :: Python :: 3
Classifier: Programming Language :: Python :: 3.8
Classifier: Programming Language :: Python :: 3.9
Classifier: Programming Language :: Python :: 3.10
Classifier: Programming Language :: Python :: 3.11
Classifier: Programming Language :: Python :: 3.12
Classifier: Topic :: Scientific/Engineering :: Artificial Intelligence
Classifier: Topic :: Text Processing :: Linguistic
Requires-Python: >=3.8
License-File: LICENSE
Requires-Dist: numpy<3.0.0,>=1.21.0
Requires-Dist: scipy<2.0.0,>=1.7.0
Requires-Dist: pandas<3.0.0,>=1.3.0
Provides-Extra: dev
Requires-Dist: pytest>=6.0; extra == "dev"
Requires-Dist: black; extra == "dev"
Requires-Dist: flake8; extra == "dev"
Requires-Dist: mypy; extra == "dev"
Provides-Extra: docs
Requires-Dist: sphinx; extra == "docs"
Requires-Dist: sphinx-rtd-theme; extra == "docs"
Dynamic: license-file
